jupyternb_task_review-1.2.4.data/data/etc/jupyter/nbconfig/notebook.d/lti-connector.json
jupyternb_task_review-1.2.4.data/data/share/jupyter/nbextensions/jupyternb-lti-connector/main.js
taskreview/__init__.py
taskreview/counter.py
taskreview/learning_module.py
taskreview/task.py
taskreview/task_database.py
taskreview/img/green_check.png
taskreview/tasks/__init__.py
taskreview/tasks/multiple_choice_task.py
taskreview/tasks/pandas_dataframe_task.py
taskreview/tasks/single_choice_task.py
taskreview/tasks/spark_dataframe_task.py
taskreview/widgets/__init__.py
taskreview/widgets/choice_widgets.py
taskreview/widgets/task_evaluation_widgets.py
jupyternb_task_review-1.2.4.dist-info/LICENSE
jupyternb_task_review-1.2.4.dist-info/METADATA
jupyternb_task_review-1.2.4.dist-info/WHEEL
jupyternb_task_review-1.2.4.dist-info/top_level.txt
jupyternb_task_review-1.2.4.dist-info/RECORD
