Metadata-Version: 2.1
Name: jupyternb-task-review
Version: 1.2.4
Summary: Integrate task review for jupyter notebook         including dataframe, single and multiple choice tasks
Home-page: UNKNOWN
Author: Lara Bertram, Anne Giesen, Johannes Kimmeyer, Michel Schwarz
Author-email: lara.bertram@study.hs-duesseldorf.de,         anne.giesen@study.hs-duesseldorf.de
License: MIT
Platform: UNKNOWN
Classifier: Development Status :: 3 - Alpha
Classifier: Topic :: Utilities
Requires-Python: >=3.6
Requires-Dist: notebook
Requires-Dist: requests
Requires-Dist: ipywidgets
